{
  "com.auth0:java-jwt" : "4.2.1",
  "com.auth0:jwks-rsa" : "0.21.2",
  "com.fasterxml.jackson.core:jackson-annotations" : "2.14.3",
  "com.fasterxml.jackson.core:jackson-core" : "2.14.3",
  "com.fasterxml.jackson.core:jackson-databind" : "2.14.3",
  "com.google.api.grpc:proto-google-common-protos" : "2.59.2",
  "com.google.code.findbugs:jsr305" : "3.0.2",
  "com.google.guava:guava" : "33.3.0-jre",
  "com.google.protobuf:protobuf-java" : "3.25.5",
  "com.google.protobuf:protobuf-java-util" : "3.25.5",
  "com.lihaoyi:sourcecode_2.13" : "0.3.0",
  "com.storm-enroute:scalameter-core_2.13" : "0.21",
  "com.storm-enroute:scalameter_2.13" : "0.21",
  "com.thesamet.scalapb.common-protos:proto-google-common-protos-scalapb_0.11_2.13" : "2.9.6-0",
  "com.thesamet.scalapb:compilerplugin_2.13" : "0.11.14",
  "com.thesamet.scalapb:lenses_2.13" : "0.11.14",
  "com.thesamet.scalapb:protoc-bridge_2.13" : "0.9.5",
  "com.thesamet.scalapb:protoc-gen_2.13" : "0.9.5",
  "com.thesamet.scalapb:scalapb-json4s_2.13" : "0.11.1",
  "com.thesamet.scalapb:scalapb-runtime-grpc_2.13" : "0.11.14",
  "com.thesamet.scalapb:scalapb-runtime_2.13" : "0.11.14",
  "com.typesafe:config" : "1.4.5",
  "commons-io:commons-io" : "2.11.0",
  "io.github.paoloboni:spray-json-derived-codecs_2.13" : "2.3.10",
  "io.grpc:grpc-api" : "1.77.0",
  "io.grpc:grpc-context" : "1.77.0",
  "io.grpc:grpc-core" : "1.77.0",
  "io.grpc:grpc-inprocess" : "1.77.0",
  "io.grpc:grpc-netty-shaded" : "1.77.0",
  "io.grpc:grpc-protobuf" : "1.77.0",
  "io.grpc:grpc-protobuf-lite" : "1.77.0",
  "io.grpc:grpc-services" : "1.77.0",
  "io.grpc:grpc-stub" : "1.77.0",
  "io.grpc:grpc-util" : "1.77.0",
  "io.opentelemetry.instrumentation:opentelemetry-grpc-1.6" : "2.9.0-alpha",
  "io.opentelemetry.instrumentation:opentelemetry-hikaricp-3.0" : "2.9.0-alpha",
  "io.opentelemetry.instrumentation:opentelemetry-instrumentation-api" : "2.9.0",
  "io.opentelemetry.instrumentation:opentelemetry-instrumentation-api-incubator" : "2.9.0-alpha",
  "io.opentelemetry.instrumentation:opentelemetry-runtime-telemetry-java8" : "2.9.0-alpha",
  "io.opentelemetry.semconv:opentelemetry-semconv" : "1.25.0-alpha",
  "io.opentelemetry:opentelemetry-api" : "1.43.0",
  "io.opentelemetry:opentelemetry-api-incubator" : "1.43.0-alpha",
  "io.opentelemetry:opentelemetry-context" : "1.43.0",
  "io.opentelemetry:opentelemetry-exporter-common" : "1.43.0",
  "io.opentelemetry:opentelemetry-exporter-otlp" : "1.43.0",
  "io.opentelemetry:opentelemetry-exporter-otlp-common" : "1.43.0",
  "io.opentelemetry:opentelemetry-exporter-prometheus" : "1.43.0-alpha",
  "io.opentelemetry:opentelemetry-exporter-sender-okhttp" : "1.43.0",
  "io.opentelemetry:opentelemetry-exporter-zipkin" : "1.43.0",
  "io.opentelemetry:opentelemetry-sdk" : "1.43.0",
  "io.opentelemetry:opentelemetry-sdk-common" : "1.43.0",
  "io.opentelemetry:opentelemetry-sdk-extension-autoconfigure-spi" : "1.43.0",
  "io.opentelemetry:opentelemetry-sdk-logs" : "1.43.0",
  "io.opentelemetry:opentelemetry-sdk-metrics" : "1.43.0",
  "io.opentelemetry:opentelemetry-sdk-testing" : "1.43.0",
  "io.opentelemetry:opentelemetry-sdk-trace" : "1.43.0",
  "io.spray:spray-json_2.13" : "1.3.6",
  "net.logstash.logback:logstash-logback-encoder" : "6.6",
  "org.apache.commons:commons-compress" : "1.24.0",
  "org.apache.pekko:pekko-actor-testkit-typed_2.13" : "1.2.1",
  "org.apache.pekko:pekko-actor-typed_2.13" : "1.2.1",
  "org.apache.pekko:pekko-actor_2.13" : "1.2.1",
  "org.apache.pekko:pekko-http-core_2.13" : "1.1.0",
  "org.apache.pekko:pekko-http-spray-json_2.13" : "1.1.0",
  "org.apache.pekko:pekko-http-testkit_2.13" : "1.1.0",
  "org.apache.pekko:pekko-http_2.13" : "1.1.0",
  "org.apache.pekko:pekko-parsing_2.13" : "1.1.0",
  "org.apache.pekko:pekko-protobuf-v3_2.13" : "1.2.1",
  "org.apache.pekko:pekko-slf4j_2.13" : "1.2.1",
  "org.apache.pekko:pekko-stream-testkit_2.13" : "1.2.1",
  "org.apache.pekko:pekko-stream_2.13" : "1.2.1",
  "org.apache.pekko:pekko-testkit_2.13" : "1.2.1",
  "org.bouncycastle:bcpkix-jdk18on" : "1.83",
  "org.bouncycastle:bcprov-jdk18on" : "1.83",
  "org.bouncycastle:bcutil-jdk18on" : "1.83",
  "org.jline:jline" : "3.27.1",
  "org.jline:jline-native" : "3.27.1",
  "org.jline:jline-reader" : "3.27.1",
  "org.jline:jline-terminal" : "3.27.1",
  "org.jline:jline-terminal-jna" : "3.14.1",
  "org.playframework.anorm:anorm-tokenizer_2.13" : "2.7.0",
  "org.playframework.anorm:anorm_2.13" : "2.7.0",
  "org.reactivestreams:reactive-streams" : "1.0.4",
  "org.reactivestreams:reactive-streams-examples" : "1.0.4",
  "org.reactivestreams:reactive-streams-tck" : "1.0.4",
  "org.sangria-graphql:sangria-spray-json_2.13" : "1.0.2",
  "org.scalactic:scalactic_2.13" : "3.2.11",
  "org.scalatest:scalatest-compatible" : "3.2.11",
  "org.scalatest:scalatest-core_2.13" : "3.2.11",
  "org.scalatest:scalatest-diagrams_2.13" : "3.2.11",
  "org.scalatest:scalatest-featurespec_2.13" : "3.2.11",
  "org.scalatest:scalatest-flatspec_2.13" : "3.2.11",
  "org.scalatest:scalatest-freespec_2.13" : "3.2.11",
  "org.scalatest:scalatest-funspec_2.13" : "3.2.11",
  "org.scalatest:scalatest-funsuite_2.13" : "3.2.11",
  "org.scalatest:scalatest-matchers-core_2.13" : "3.2.11",
  "org.scalatest:scalatest-mustmatchers_2.13" : "3.2.11",
  "org.scalatest:scalatest-propspec_2.13" : "3.2.11",
  "org.scalatest:scalatest-refspec_2.13" : "3.2.11",
  "org.scalatest:scalatest-shouldmatchers_2.13" : "3.2.11",
  "org.scalatest:scalatest-wordspec_2.13" : "3.2.11",
  "org.scalatest:scalatest_2.13" : "3.2.11",
  "org.scalaz:scalaz-scalacheck-binding_2.13" : "7.2.33-scalacheck-1.15"
}
